README.md
setup.py
rifbot/GqlClient.py
rifbot/RifbotClient.py
rifbot/RootOptions.py
rifbot/SchedulerClient.py
rifbot/StrategyRepositoryClient.py
rifbot/__init__.py
rifbot/dataset_generator.py
rifbot/gql_queries.py
rifbot/tools.py
rifbot.egg-info/PKG-INFO
rifbot.egg-info/SOURCES.txt
rifbot.egg-info/dependency_links.txt
rifbot.egg-info/requires.txt
rifbot.egg-info/top_level.txt