Metadata-Version: 2.1
Name: rifbot
Version: 0.59
Summary: Python API for Riftrading Rifbot
Home-page: https://www.riftrading.com
Author: riftrading
Author-email: admin@riftrading.com
License: UNKNOWN
Platform: UNKNOWN
